<!DOCTYPE node PUBLIC "-//freedesktop//DTD D-BUS Object Introspection 1.0//EN" "http://www.freedesktop.org/standards/dbus/1.0/introspect.dtd">
<node>
  <interface name="org.deepin.DisplayManager.RemoteDisplayFactory.Session">
    <property name="UserName" type="s" access="read"/>
    <property name="Address" type="s" access="read"/>
  </interface>
  <interface name="org.deepin.DisplayManager.RemoteDisplayFactory">
    <method name="CreateRemoteGreeterDisplay">
      <arg name="remote_id" direction="in" type="y"/>
      <arg name="width" direction="in" type="u"/>
      <arg name="height" direction="in" type="u"/>
      <arg name="address" direction="in" type="s"/>
      <arg name="session" direction="out" type="o"/>
    </method>
    <method name="CreateSingleLogonSession">
      <arg name="remote_id" direction="in" type="y"/>
      <arg name="width" direction="in" type="u"/>
      <arg name="height" direction="in" type="u"/>
      <arg name="user_name" direction="in" type="s"/>"
      <arg name="address" direction="in" type="s"/>
      <arg name="session" direction="out" type="o"/>
    </method>
  </interface>
</node>